{
  "environment": "DEV",
  "auth0_domain": "dev.mozilla-dev.auth0.com",
  "cdn_domain": "localhost:3000",
  "LDAP_connection_name": "Mozilla-LDAP-Dev",
  "iam_api_domain": "iam.api.dev.sso.allizom.org",
  "logout_url": "https://dev.mozilla-dev.auth0.com/v2/logout?returnTo=https://sso.allizom.org/signout.html",
  "sso_dashboard_url": "https://sso.allizom.org",
  "GTM_ID": "GTM-T2N2BRW",
  "client_ID": "ePsG2xvde5KFkUviYJ0I7VtpiR7fGo0i",
  "features": {
    "autologin": "true",
    "iam_api_lookup": "true",
    "maintenance_mode": "false",
    "header_banner_pre": "true"
  },
  "supportedLoginMethods": [ "github", "google-oauth2", "firefoxaccounts", "email" ],
  "csp": "default-src *",
  "displayNames": {
    "github": "GitHub",
    "google-oauth2": "Google",
    "firefoxaccounts": "Firefox Accounts",
    "email": "email"
  }
}
